README.md
setup.py
distkit/__init__.py
distkit/binomial.py
distkit/gaussian.py
distkit/general.py
distkit.egg-info/PKG-INFO
distkit.egg-info/SOURCES.txt
distkit.egg-info/dependency_links.txt
distkit.egg-info/not-zip-safe
distkit.egg-info/top_level.txt
test/test.py