Metadata-Version: 2.1
Name: distkit
Version: 1.7
Summary: Gaussian and Binomial distributions
Home-page: https://github.com/abhinav314/distkit
Author: Abhinav Chanda
Author-email: abhinav468@gmail.com
License: UNKNOWN
Platform: UNKNOWN
Classifier: Programming Language :: Python :: 3
Classifier: License :: OSI Approved :: MIT License
Classifier: Operating System :: OS Independent
Requires-Python: >=3.0
